apscale_gui/__init__.py
apscale_gui/__main__.py
apscale_gui/apscale_gui.py
apscale_gui/_user_data/user_data.txt
apscale_gui-3.1.0.dist-info/LICENSE
apscale_gui-3.1.0.dist-info/METADATA
apscale_gui-3.1.0.dist-info/WHEEL
apscale_gui-3.1.0.dist-info/entry_points.txt
apscale_gui-3.1.0.dist-info/top_level.txt
apscale_gui-3.1.0.dist-info/RECORD
