Metadata-Version: 2.1
Name: apscale_gui
Version: 3.1.0
Summary: Advanced Pipeline for Simple yet Comprehensive AnaLysEs of DNA metabarcoding data - Graphical User Interface
Home-page: https://github.com/TillMacher/apscale_gui
Author: Till-Hendrik Macher
Author-email: macher@uni-trier.de
License: MIT
Classifier: Programming Language :: Python :: 3
Classifier: License :: OSI Approved :: MIT License
Classifier: Operating System :: OS Independent
Requires-Python: >=3.12
License-File: LICENSE
Requires-Dist: apscale>=4.1.4
Requires-Dist: apscale-blast>=1.2.7
Requires-Dist: boldigger3>=2.1.4
Requires-Dist: demultiplexer2>=1.1.6
Requires-Dist: ete3>=3.1.3
Requires-Dist: lxml-html-clean>=0.4.2
Requires-Dist: playwright>=1.54.0
Requires-Dist: pandas>=2.3.1
Requires-Dist: numpy>=2.3.2
Requires-Dist: streamlit>=1.48.1
Requires-Dist: streamlit-file-browser>=3.2.22
Requires-Dist: scipy>=1.16.1
Requires-Dist: cutadapt>=5.1
Requires-Dist: update-checker>=0.18.0
Requires-Dist: powerlaw>=1.5
Requires-Dist: requests>=2.32.3
Requires-Dist: beautifulsoup4>=4.13.4
Requires-Dist: lxml>=6.0.0
Requires-Dist: asyncio>=4.0.0
